mkdocs_rtd_mklab
