Metadata-Version: 1.0
Name: mkdocs-rtd-mklab
Version: 1.8.0
Summary: The readthedocs theme for mkdocs,Replacement of Google fonts, etc.
Home-page: UNKNOWN
Author: mklab
Author-email: mklabs@163.com
License: MIT Licence
Keywords: pip,readthedocs-mklab,theme
Platform: any
